odoo/addons/website_sale_product_minimal_price/README.rst
odoo/addons/website_sale_product_minimal_price/__init__.py
odoo/addons/website_sale_product_minimal_price/__manifest__.py
odoo/addons/website_sale_product_minimal_price/controllers/__init__.py
odoo/addons/website_sale_product_minimal_price/controllers/main.py
odoo/addons/website_sale_product_minimal_price/demo/assets.xml
odoo/addons/website_sale_product_minimal_price/i18n/ca.po
odoo/addons/website_sale_product_minimal_price/i18n/es.po
odoo/addons/website_sale_product_minimal_price/i18n/fr.po
odoo/addons/website_sale_product_minimal_price/i18n/website_sale_product_minimal_price.pot
odoo/addons/website_sale_product_minimal_price/models/__init__.py
odoo/addons/website_sale_product_minimal_price/models/product_template.py
odoo/addons/website_sale_product_minimal_price/readme/CONFIGURE.rst
odoo/addons/website_sale_product_minimal_price/readme/CONTRIBUTORS.rst
odoo/addons/website_sale_product_minimal_price/readme/DESCRIPTION.rst
odoo/addons/website_sale_product_minimal_price/readme/HISTORY.rst
odoo/addons/website_sale_product_minimal_price/readme/USAGE.rst
odoo/addons/website_sale_product_minimal_price/static/description/icon.png
odoo/addons/website_sale_product_minimal_price/static/description/index.html
odoo/addons/website_sale_product_minimal_price/static/src/js/test_product_with_no_prices_tour.js
odoo/addons/website_sale_product_minimal_price/static/src/js/website_sale_product_minimal_price.js
odoo/addons/website_sale_product_minimal_price/static/src/js/website_sale_product_minimal_price_tour.js
odoo/addons/website_sale_product_minimal_price/static/src/xml/website_sale_product_minimal_price.xml
odoo/addons/website_sale_product_minimal_price/tests/__init__.py
odoo/addons/website_sale_product_minimal_price/tests/test_product_with_no_prices.py
odoo/addons/website_sale_product_minimal_price/tests/test_website_sale_product_minimal_price.py
odoo/addons/website_sale_product_minimal_price/views/assets.xml
odoo12_addon_website_sale_product_minimal_price-12.0.2.0.4.dist-info/METADATA
odoo12_addon_website_sale_product_minimal_price-12.0.2.0.4.dist-info/WHEEL
odoo12_addon_website_sale_product_minimal_price-12.0.2.0.4.dist-info/top_level.txt
odoo12_addon_website_sale_product_minimal_price-12.0.2.0.4.dist-info/RECORD
